Workbook

Sheet Cover
B2: LULULEMON ATHLETICA (LULU)
B3: Equity Valuation & Competitive Analysis
B4: FIN 4395 — Capstone Senior Project in Finance | UT Dallas
B5: Analyst: Ryan Neumann
B6: Date: Spring 2026
B10: Sheet | C10: Description
B11: Cover | C11: Navigation, project overview
B12: Assumptions | C12: All model inputs (revenue growth, margins, WACC, etc.)
B13: DCF Model | C13: 10-year projection + terminal value + equity bridge
B14: Comps | C14: EV/EBITDA, P/E, EV/Revenue multiples for 8 peers
B15: Football Field | C15: Summary valuation range chart
B16: Sensitivity | C16: WACC × Terminal Growth Rate sensitivity tables

Sheet Assumptions
B2: MODEL ASSUMPTIONS — LULULEMON (LULU)
B3: Blue = hardcoded input | Black = calculated
B5: REVENUE GROWTH ASSUMPTIONS
B6: FY2024A Revenue ($mm) | C6: 10583 | D6: Source: LULU 10-K FY2024
B7: FY2025E Growth Rate | C7: 0.12 | D7: Analyst estimate
B8: FY2026E Growth Rate | C8: 0.11 | D8: Analyst estimate
B9: FY2027E Growth Rate | C9: 0.1 | D9: Analyst estimate
B10: FY2028E Growth Rate | C10: 0.09 | D10: Analyst estimate
B11: FY2029E Growth Rate | C11: 0.08 | D11: Analyst estimate
B12: Terminal Growth Rate | C12: 0.03 | D12: Long-run GDP proxy
B14: MARGIN ASSUMPTIONS
B15: Gross Margin | C15: 0.575 | D15: Source: LULU 10-K FY2024
B16: EBITDA Margin | C16: 0.245 | D16: Analyst estimate
B17: D&A (% of Revenue) | C17: 0.045 | D17: Historical avg
B18: EBIT Margin | C18: =C15-C17 -> 0.53 | D18: Calculated
B19: Tax Rate | C19: 0.265 | D19: Effective rate FY2024
B20: Net Income Margin | C20: 0.165 | D20: Source: LULU 10-K FY2024
B22: BALANCE SHEET / FCF ASSUMPTIONS
B23: CapEx (% of Revenue) | C23: 0.055 | D23: Source: LULU 10-K FY2024
B24: Change in NWC (% of Rev Δ) | C24: 0.04 | D24: Analyst estimate
B26: WACC ASSUMPTIONS
B27: Risk-Free Rate | C27: 0.043 | D27: 10-yr UST yield
B28: Equity Risk Premium | C28: 0.055 | D28: Damodaran estimate
B29: Beta (LULU) | C29: 1.42 | D29: Source: Bloomberg
B30: Cost of Equity | C30: =C27+C29*C28 -> 0.1211 | D30: CAPM
B31: Pre-Tax Cost of Debt | C31: 0.055 | D31: Analyst estimate
B32: Debt Weight | C32: 0.08 | D32: Market-value based
B33: Equity Weight | C33: =1-C32 -> 0.92 | D33: Calculated
B34: WACC | C34: =C30*C33+C31*(1-C19)*C32 -> 0.114646 | D34: Calculated
B37: VALUATION MULTIPLES (for Comps sheet)
B38: EV/EBITDA — Entry Multiple | C38: 25 | D38: Based on peer median
B39: EV/Revenue — Entry Multiple | C39: 4.5 | D39: Based on peer median

Sheet DCF Model
B2: DISCOUNTED CASH FLOW MODEL — LULULEMON ATHLETICA (LULU)
B3: $ in millions unless noted | Fiscal year ends January
B5: ($mm) | C5: FY2024A | D5: FY2025E | E5: FY2026E | F5: FY2027E | G5: FY2028E | H5: FY2029E
B6: Revenue | C6: =Assumptions!C6 -> 10583 | D6: =C6*(1+Assumptions!C7) -> 11852.96 | E6: =D6*(1+Assumptions!C8) -> 13156.786 | F6: =E6*(1+Assumptions!C9) -> 14472.464 | G6: =F6*(1+Assumptions!C10) -> 15774.986 | H6: =G6*(1+Assumptions!C11) -> 17036.985
B7: YoY Growth | D7: =(D6-C6)/C6 -> 0.12 | E7: =(E6-D6)/D6 -> 0.11 | F7: =(F6-E6)/E6 -> 0.1 | G7: =(G6-F6)/F6 -> 0.09
B8: Gross Profit | C8: =C6*Assumptions!$C$15 -> 6085.225 | D8: =D6*Assumptions!$C$15 -> 6815.452 | E8: =E6*Assumptions!$C$15 -> 7565.1517 | F8: =F6*Assumptions!$C$15 -> 8321.6669 | G8: =G6*Assumptions!$C$15 -> 9070.6169 | H8: =H6*Assumptions!$C$15 -> 9796.2663
B9: EBITDA | C9: =C6*Assumptions!$C$16 -> 2592.835 | D9: =D6*Assumptions!$C$16 -> 2903.9752 | E9: =E6*Assumptions!$C$16 -> 3223.4125 | F9: =F6*Assumptions!$C$16 -> 3545.7537 | G9: =G6*Assumptions!$C$16 -> 3864.8716 | H9: =H6*Assumptions!$C$16 -> 4174.0613
B10: EBITDA Margin | C10: =C9/C6 -> 0.245 | D10: =D9/D6 -> 0.245 | E10: =E9/E6 -> 0.245 | F10: =F9/F6 -> 0.245 | G10: =G9/G6 -> 0.245 | H10: =H9/H6 -> 0.245
B11: Less: D&A | C11: =-C6*Assumptions!$C$17 -> -476.235 | D11: =-D6*Assumptions!$C$17 -> -533.3832 | E11: =-E6*Assumptions!$C$17 -> -592.05535 | F11: =-F6*Assumptions!$C$17 -> -651.26089 | G11: =-G6*Assumptions!$C$17 -> -709.87437 | H11: =-H6*Assumptions!$C$17 -> -766.66432
B12: EBIT | C12: =C9+C11 -> 2116.6 | D12: =D9+D11 -> 2370.592 | E12: =E9+E11 -> 2631.3571 | F12: =F9+F11 -> 2894.4928 | G12: =G9+G11 -> 3154.9972 | H12: =H9+H11 -> 3407.397
B13: Less: Taxes | C13: =-C12*Assumptions!$C$21 -> 0 | D13: =-D12*Assumptions!$C$21 -> 0 | E13: =-E12*Assumptions!$C$21 -> 0 | F13: =-F12*Assumptions!$C$21 -> 0 | G13: =-G12*Assumptions!$C$21 -> 0 | H13: =-H12*Assumptions!$C$21 -> 0
B14: NOPAT | C14: =C12+C13 -> 2116.6 | D14: =D12+D13 -> 2370.592 | E14: =E12+E13 -> 2631.3571 | F14: =F12+F13 -> 2894.4928 | G14: =G12+G13 -> 3154.9972 | H14: =H12+H13 -> 3407.397
B15: Add-back: D&A | C15: =-C11 -> 476.235 | D15: =-D11 -> 533.3832 | E15: =-E11 -> 592.05535 | F15: =-F11 -> 651.26089 | G15: =-G11 -> 709.87437 | H15: =-H11 -> 766.66432
B16: Less: CapEx | C16: =-C6*Assumptions!$C$23 -> -582.065 | D16: =-D6*Assumptions!$C$23 -> -651.9128 | E16: =-E6*Assumptions!$C$23 -> -723.62321 | F16: =-F6*Assumptions!$C$23 -> -795.98553 | G16: =-G6*Assumptions!$C$23 -> -867.62423 | H16: =-H6*Assumptions!$C$23 -> -937.03416
B17: Less: Change in NWC | C17: - | D17: =-(D6-C6)*Assumptions!$C$24 -> -50.7984 | E17: =-(E6-D6)*Assumptions!$C$24 -> -52.153024 | F17: =-(F6-E6)*Assumptions!$C$24 -> -52.627142 | G17: =-(G6-F6)*Assumptions!$C$24 -> -52.100871
B18: Free Cash Flow to Firm (FCFF) | C18: =SUM(C14:C17) -> 2010.77 | D18: =SUM(D14:D17) -> 2201.264 | E18: =SUM(E14:E17) -> 2447.6362 | F18: =SUM(F14:F17) -> 2697.141 | G18: =SUM(G14:G17) -> 2945.1465 | H18: =SUM(H14:H17) -> 3237.0271
B20: Discount Period | D20: 1 | E20: 2 | F20: 3 | G20: 4 | H20: 5
B21: PV of FCFF | C21: - | D21: =D18/(1+Assumptions!$C$34)^D20 -> 1974.8548 | E21: =E18/(1+Assumptions!$C$34)^E20 -> 1970.0305 | F21: =F18/(1+Assumptions!$C$34)^F20 -> 1947.5686 | G21: =G18/(1+Assumptions!$C$34)^G20 -> 1907.9151 | H21: =H18/(1+Assumptions!$C$34)^H20 -> 1881.315
B23: TERMINAL VALUE
B24: Terminal Year FCFF | C24: =H18*(1+Assumptions!C12) -> 3334.1379
B25: Terminal Value (Gordon Growth) | C25: =C24/(Assumptions!C34-Assumptions!C12) -> 39389.197
B26: PV of Terminal Value | C26: =C25/(1+Assumptions!C34)^5 -> 22892.452
B28: ENTERPRISE VALUE BRIDGE
B29: Sum of PV (FCFF, FY25-FY29) | C29: =SUM(D21:H21) -> 9681.6841
B30: PV of Terminal Value | C30: =C26 -> 22892.452
B31: Enterprise Value | C31: =C29+C30 -> 32574.136
B32: Less: Net Debt | C32: 785 | D32: Source: LULU 10-K FY2024
B33: Equity Value | C33: =C31-C32 -> 31789.136
B34: Diluted Shares Outstanding (mm) | C34: 127.5 | D34: Source: LULU 10-K FY2024
B35: Implied Share Price | C35: =C33/C34 -> 249.32656

Sheet Comps
B2: COMPARABLE COMPANY ANALYSIS — LULULEMON (LULU)
B3: $ in millions | LTM figures | Source: Bloomberg / Company Filings
B5: Company | C5: Ticker | D5: Mkt Cap ($mm) | E5: EV ($mm) | F5: Revenue ($mm) | G5: EBITDA ($mm) | H5: EV/EBITDA | I5: EV/Revenue | J5: P/E
B6: Lululemon | C6: LULU | D6: 35400 | E6: 36185 | F6: 10583 | G6: 2593 | H6: =IF(G6<>0,E6/G6,"-") -> 13.954879 | I6: =IF(F6<>0,E6/F6,"-") -> 3.4191628 | J6: -
B7: Nike | C7: NKE | D7: 96200 | E7: 104600 | F7: 51362 | G7: 6312 | H7: =IF(G7<>0,E7/G7,"-") -> 16.57161 | I7: =IF(F7<>0,E7/F7,"-") -> 2.0365251 | J7: -
B8: Adidas | C8: ADDYY | D8: 38500 | E8: 41800 | F8: 24740 | G8: 2720 | H8: =IF(G8<>0,E8/G8,"-") -> 15.367647 | I8: =IF(F8<>0,E8/F8,"-") -> 1.6895715 | J8: -
B9: Under Armour | C9: UAA | D9: 3500 | E9: 4900 | F9: 5300 | G9: 380 | H9: =IF(G9<>0,E9/G9,"-") -> 12.894737 | I9: =IF(F9<>0,E9/F9,"-") -> 0.9245283 | J9: -
B10: Athleta / Gap | C10: GPS | D10: 8200 | E10: 9500 | F10: 15600 | G10: 960 | H10: =IF(G10<>0,E10/G10,"-") -> 9.8958333 | I10: =IF(F10<>0,E10/F10,"-") -> 0.60897436 | J10: -
B11: On Holding | C11: ONON | D11: 27000 | E11: 26800 | F11: 2540 | G11: 380 | H11: =IF(G11<>0,E11/G11,"-") -> 70.526316 | I11: =IF(F11<>0,E11/F11,"-") -> 10.551181 | J11: -
B12: Deckers Outdoor | C12: DECK | D12: 20000 | E12: 19800 | F12: 4840 | G12: 940 | H12: =IF(G12<>0,E12/G12,"-") -> 21.06383 | I12: =IF(F12<>0,E12/F12,"-") -> 4.0909091 | J12: -
B13: VF Corporation | C13: VFC | D13: 4100 | E13: 8800 | F13: 11800 | G13: 820 | H13: =IF(G13<>0,E13/G13,"-") -> 10.731707 | I13: =IF(F13<>0,E13/F13,"-") -> 0.74576271 | J13: -
B15: Mean | H15: =AVERAGE(H7:H14) -> 22.435954 | I15: =AVERAGE(I7:I14) -> 2.949636
B16: Median | H16: =MEDIAN(H7:H14) -> 15.367647 | I16: =MEDIAN(I7:I14) -> 1.6895715
B17: High | H17: =MAX(H7:H14) -> 70.526316 | I17: =MAX(I7:I14) -> 10.551181
B18: Low | H18: =MIN(H7:H14) -> 9.8958333 | I18: =MIN(I7:I14) -> 0.60897436
B20: LULU COMPS-DERIVED PRICE TARGET
B21: EV/EBITDA — Median Multiple | C21: =H16 -> 15.367647 | D21: Implied EV ($mm) | E21: =C21*'DCF Model'!C9 -> 39845.773 | F21: Implied Share Price | G21: =(E21-'DCF Model'!C32)/'DCF Model'!C34 -> 306.35901
B22: EV/Revenue — Median Multiple | C22: =I16 -> 1.6895715 | D22: Implied EV ($mm) | E22: =C22*'DCF Model'!C6 -> 17880.736 | F22: Implied Share Price | G22: =(E22-'DCF Model'!C32)/'DCF Model'!C34 -> 134.0842

Sheet Val Sum
B2: VALUATION SUMMARY
B3: Implied share price ranges by methodology
B5: Methodology | C5: Low | D5: Mid | E5: High
B6: DCF (Base Case) | C6: ='DCF Model'!C35*0.88 -> 219.40737 | D6: ='DCF Model'!C35 -> 249.32656 | E6: ='DCF Model'!C35*1.12 -> 279.24574
B7: EV/EBITDA Comps | C7: =Comps!G21*0.9 -> 275.7231 | D7: =Comps!G21 -> 306.35901 | E7: =Comps!G21*1.1 -> 336.99491
B8: EV/Revenue Comps | C8: =Comps!G22*0.9 -> 120.67578 | D8: =Comps!G22 -> 134.0842 | E8: =Comps!G22*1.1 -> 147.49262
B9: 52-Week Range | C9: 250 | D9: 355 | E9: 425
B10: Analyst Consensus | C10: 310 | D10: 365 | E10: 420

Sheet Sensitivity
B2: SENSITIVITY ANALYSIS — DCF IMPLIED SHARE PRICE
B3: Implied share price ($) | Rows = WACC | Cols = Terminal Growth Rate
B5: WACC \ TGR | C5: 0.02 | D5: 0.025 | E5: 0.03 | F5: 0.035 | G5: 0.04
B6: 0.08 | C6: 361 | D6: 367 | E6: 373 | F6: 379 | G6: 385
B7: 0.085 | C7: 352 | D7: 358 | E7: 364 | F7: 370 | G7: 376
B8: 0.09 | C8: 343 | D8: 349 | E8: 355 | F8: 361 | G8: 367
B9: 0.095 | C9: 334 | D9: 340 | E9: 346 | F9: 352 | G9: 358
B10: 0.1 | C10: 325 | D10: 331 | E10: 337 | F10: 343 | G10: 349
B11: 0.105 | C11: 316 | D11: 322 | E11: 328 | F11: 334 | G11: 340
B12: 0.11 | C12: 307 | D12: 313 | E12: 319 | F12: 325 | G12: 331
B14: Note: Green = premium to current price | Red = discount | Sensitivity built around base WACC 9.0%, TGR 3.0%
